sparkle_log/__about__.py
sparkle_log/__init__.py
sparkle_log/__main__.py
sparkle_log/as_context_manager.py
sparkle_log/as_decorator.py
sparkle_log/custom_types.py
sparkle_log/drive_space.py
sparkle_log/graphs.py
sparkle_log/log_writer.py
sparkle_log/py.typed
sparkle_log/scheduler.py
sparkle_log/ui.py
sparkle_log-0.4.0.dist-info/AUTHORS.md
sparkle_log-0.4.0.dist-info/LICENSE
sparkle_log-0.4.0.dist-info/METADATA
sparkle_log-0.4.0.dist-info/WHEEL
sparkle_log-0.4.0.dist-info/entry_points.txt
sparkle_log-0.4.0.dist-info/RECORD
