Metadata-Version: 2.1
Name: sparkle-log
Version: 0.4.0
Summary: Write sparkline graphs of CPU and memory usage to your logs.
Home-page: https://github.com/matthewdeanmartin/sparkle_log
License: MIT
Keywords: monitoring,logging
Author: Matthew Martin
Author-email: matthewdeanmartin@gmail.com
Requires-Python: >=3.9
Classifier: Development Status :: 4 - Beta
Classifier: Intended Audience :: Developers
Classifier: License :: OSI Approved :: MIT License
Classifier: Operating System :: OS Independent
Classifier: Programming Language :: Python
Classifier: Programming Language :: Python :: 3
Classifier: Programming Language :: Python :: 3.9
Classifier: Programming Language :: Python :: 3.10
Classifier: Programming Language :: Python :: 3.11
Classifier: Programming Language :: Python :: 3.12
Requires-Dist: colorlog (>=6.8.0)
Requires-Dist: psutil
Requires-Dist: schedule
Requires-Dist: sparklines (>=0.5.0)
Project-URL: Bug Tracker, https://github.com/matthewdeanmartin/sparkle_log/issues
Project-URL: Change Log, https://github.com/matthewdeanmartin/sparkle_log/blob/main/CHANGELOG.md
Project-URL: Documentation, https://matthewdeanmartin.github.io/sparkle_log/sparkle_log/index.html
Project-URL: Repository, https://github.com/matthewdeanmartin/sparkle_log
